aprsd_twitter_plugin/__init__.py
aprsd_twitter_plugin/twitter.py
aprsd_twitter_plugin/conf/__init__.py
aprsd_twitter_plugin/conf/opts.py
aprsd_twitter_plugin/conf/twitter.py
aprsd_twitter_plugin-0.5.0.dist-info/LICENSE
aprsd_twitter_plugin-0.5.0.dist-info/METADATA
aprsd_twitter_plugin-0.5.0.dist-info/WHEEL
aprsd_twitter_plugin-0.5.0.dist-info/entry_points.txt
aprsd_twitter_plugin-0.5.0.dist-info/pbr.json
aprsd_twitter_plugin-0.5.0.dist-info/top_level.txt
aprsd_twitter_plugin-0.5.0.dist-info/RECORD
